README.md
setup.cfg
setup.py
biopax_explorer/__init__.py
biopax_explorer.egg-info/PKG-INFO
biopax_explorer.egg-info/SOURCES.txt
biopax_explorer.egg-info/dependency_links.txt
biopax_explorer.egg-info/not-zip-safe
biopax_explorer.egg-info/requires.txt
biopax_explorer.egg-info/top_level.txt
biopax_explorer/biopax/__init__.py
biopax_explorer/biopax/bindingfeature.py
biopax_explorer/biopax/biochemicalpathwaystep.py
biopax_explorer/biopax/biochemicalreaction.py
biopax_explorer/biopax/biosource.py
biopax_explorer/biopax/catalysis.py
biopax_explorer/biopax/cellularlocationvocabulary.py
biopax_explorer/biopax/cellvocabulary.py
biopax_explorer/biopax/chemicalstructure.py
biopax_explorer/biopax/complex.py
biopax_explorer/biopax/complexassembly.py
biopax_explorer/biopax/control.py
biopax_explorer/biopax/controlledvocabulary.py
biopax_explorer/biopax/conversion.py
biopax_explorer/biopax/covalentbindingfeature.py
biopax_explorer/biopax/degradation.py
biopax_explorer/biopax/deltag.py
biopax_explorer/biopax/dna.py
biopax_explorer/biopax/dnareference.py
biopax_explorer/biopax/dnaregion.py
biopax_explorer/biopax/dnaregionreference.py
biopax_explorer/biopax/entity.py
biopax_explorer/biopax/entityfeature.py
biopax_explorer/biopax/entityreference.py
biopax_explorer/biopax/entityreferencetypevocabulary.py
biopax_explorer/biopax/evidence.py
biopax_explorer/biopax/evidencecodevocabulary.py
biopax_explorer/biopax/experimentalform.py
biopax_explorer/biopax/experimentalformvocabulary.py
biopax_explorer/biopax/fragmentfeature.py
biopax_explorer/biopax/gene.py
biopax_explorer/biopax/geneticinteraction.py
biopax_explorer/biopax/interaction.py
biopax_explorer/biopax/interactionvocabulary.py
biopax_explorer/biopax/kprime.py
biopax_explorer/biopax/modificationfeature.py
biopax_explorer/biopax/modulation.py
biopax_explorer/biopax/molecularinteraction.py
biopax_explorer/biopax/pathway.py
biopax_explorer/biopax/pathwaystep.py
biopax_explorer/biopax/phenotypevocabulary.py
biopax_explorer/biopax/physicalentity.py
biopax_explorer/biopax/protein.py
biopax_explorer/biopax/proteinreference.py
biopax_explorer/biopax/provenance.py
biopax_explorer/biopax/publicationxref.py
biopax_explorer/biopax/relationshiptypevocabulary.py
