Metadata-Version: 2.1
Name: biopax-explorer
Version: 1.2
Summary: A python library for BIOPAX manipulation
Home-page: https://forgemia.inra.fr/pegase/biopax-explorer
Author: FJR Moreews
Author-email: fjrmoreews@gmail.com
License: MIT
Platform: Posix; MacOS X;
Classifier: Development Status :: 4 - Beta
Classifier: Intended Audience :: Developers
Classifier: Intended Audience :: Science/Research
Classifier: License :: OSI Approved :: MIT License
Classifier: Programming Language :: Python :: 3.8
Classifier: Programming Language :: Python :: 3.9
Classifier: Programming Language :: Python :: 3.10
Classifier: Programming Language :: Python :: 3.11
Classifier: Topic :: Scientific/Engineering
Classifier: Topic :: Scientific/Engineering :: Bio-Informatics
Requires-Python: >=3.8.10
Provides-Extra: testing
